Exceptions/__init__.py
Exceptions/exceptions.py
surfquake-0.1.7.dist-info/licenses/LICENSE
surfquakecore/__init__.py
surfquakecore/Structures/__init__.py
surfquakecore/Structures/obspy_stats_keys.py
surfquakecore/Structures/structures.py
surfquakecore/arrayanalysis/__init__.py
surfquakecore/arrayanalysis/array_analysis.py
surfquakecore/arrayanalysis/beamforming_tools.py
surfquakecore/arrayanalysis/beamrun.py
surfquakecore/binaries/__init__.py
surfquakecore/binaries/linux_bin/__init__.py
surfquakecore/binaries/linux_bin/FOCMEC/focmec
surfquakecore/binaries/linux_bin/NLL/Grid2GMT
surfquakecore/binaries/linux_bin/NLL/Grid2Time
surfquakecore/binaries/linux_bin/NLL/GridCascadingDecimate
surfquakecore/binaries/linux_bin/NLL/Loc2ddct
surfquakecore/binaries/linux_bin/NLL/Loc2ssst
surfquakecore/binaries/linux_bin/NLL/LocSum
surfquakecore/binaries/linux_bin/NLL/NLDiffLoc
surfquakecore/binaries/linux_bin/NLL/NLLoc
surfquakecore/binaries/linux_bin/NLL/NLLoc_func_test
surfquakecore/binaries/linux_bin/NLL/PhsAssoc
surfquakecore/binaries/linux_bin/NLL/Time2Angles
surfquakecore/binaries/linux_bin/NLL/Time2EQ
surfquakecore/binaries/linux_bin/NLL/Vel2Grid
surfquakecore/binaries/linux_bin/NLL/Vel2Grid3D
surfquakecore/binaries/linux_bin/NLL/fmm2grid
surfquakecore/binaries/linux_bin/NLL/fpfit2hyp
surfquakecore/binaries/linux_bin/NLL/grid2scat
surfquakecore/binaries/linux_bin/NLL/hypoe2hyp
surfquakecore/binaries/linux_bin/NLL/interface2fmm
surfquakecore/binaries/linux_bin/NLL/mag_func_test
surfquakecore/binaries/linux_bin/NLL/oct2grid
surfquakecore/binaries/linux_bin/NLL/scat2latlon
surfquakecore/binaries/linux_bin/NLL/sphfd_SWR_NLL
surfquakecore/binaries/linux_bin/NLL/ttime_func_test
surfquakecore/binaries/linux_bin/REAL/REAL
surfquakecore/binaries/linux_bin/mti_green/dimen1.inc
surfquakecore/binaries/linux_bin/mti_green/dimen2.inc
surfquakecore/binaries/linux_bin/mti_green/elemse
surfquakecore/binaries/linux_bin/mti_green/gr_xyz
surfquakecore/binaries/linux_bin/mti_green/param.inc
surfquakecore/binaries/mac_bin/__init__.py
surfquake-0.1.7.dist-info/METADATA
surfquake-0.1.7.dist-info/WHEEL
surfquake-0.1.7.dist-info/entry_points.txt
surfquake-0.1.7.dist-info/top_level.txt
surfquake-0.1.7.dist-info/RECORD
