Metadata-Version: 2.4
Name: surfquake
Version: 0.1.7
Summary: SurfQuake Core
Author-email: Roberto Cabieces & Thiago Junqueira <rcabdia@roa.es>
Project-URL: Homepage, https://projectisp.github.io/surfquaketutorial.github.io/
Classifier: Programming Language :: Python :: 3
Classifier: License :: OSI Approved :: MIT License
Classifier: Operating System :: OS Independent
Requires-Python: >=3.9
License-File: LICENSE
Requires-Dist: python-dateutil~=2.8.2
Requires-Dist: numpy~=1.26.1
Requires-Dist: obspy~=1.4.0
Requires-Dist: pyproj~=3.6.1
Requires-Dist: pandas~=2.1.2
Requires-Dist: tensorflow~=2.15.0
Requires-Dist: sourcespec==1.7
Requires-Dist: PyYAML~=6.0.1
Requires-Dist: scipy~=1.11.3
Requires-Dist: matplotlib~=3.8.4
Requires-Dist: Cartopy~=0.23.0
Requires-Dist: pywavelets~=1.6.0
Requires-Dist: nitime~=0.11
Requires-Dist: cython~=3.0.11
Requires-Dist: deprecated~=1.2.15
Dynamic: license-file
